source_harvest/__init__.py
source_harvest/config_migrations.py
source_harvest/manifest.yaml
source_harvest/run.py
source_harvest/schemas/billable_rates.json
source_harvest/schemas/clients.json
source_harvest/schemas/company.json
source_harvest/schemas/contacts.json
source_harvest/schemas/cost_rates.json
source_harvest/schemas/estimate_item_categories.json
source_harvest/schemas/estimate_messages.json
source_harvest/schemas/estimates.json
source_harvest/schemas/expense_categories.json
source_harvest/schemas/expenses.json
source_harvest/schemas/expenses_categories.json
source_harvest/schemas/expenses_clients.json
source_harvest/schemas/expenses_projects.json
source_harvest/schemas/expenses_team.json
source_harvest/schemas/invoice_item_categories.json
source_harvest/schemas/invoice_messages.json
source_harvest/schemas/invoice_payments.json
source_harvest/schemas/invoices.json
source_harvest/schemas/project_assignments.json
source_harvest/schemas/project_budget.json
source_harvest/schemas/projects.json
source_harvest/schemas/roles.json
source_harvest/schemas/task_assignments.json
source_harvest/schemas/tasks.json
source_harvest/schemas/time_clients.json
source_harvest/schemas/time_entries.json
source_harvest/schemas/time_projects.json
source_harvest/schemas/time_tasks.json
source_harvest/schemas/time_team.json
source_harvest/schemas/uninvoiced.json
source_harvest/schemas/user_assignments.json
source_harvest/schemas/users.json
source_harvest/source.py
airbyte_source_harvest-1.0.19.dist-info/METADATA
airbyte_source_harvest-1.0.19.dist-info/WHEEL
airbyte_source_harvest-1.0.19.dist-info/entry_points.txt
airbyte_source_harvest-1.0.19.dist-info/RECORD
